idem_k8s/conf.py
idem_k8s/version.py
idem_k8s/acct/k8s/init.py
idem_k8s/autogen/k8s/init.py
idem_k8s/autogen/k8s/openapi_spec_parser.py
idem_k8s/autogen/k8s/plugin.py
idem_k8s/autogen/k8s/template.py
idem_k8s/autogen/k8s/type.py
idem_k8s/exec/k8s/init.py
idem_k8s/exec/k8s/apiregistration_k8s_io/v1/api_service.py
idem_k8s/exec/k8s/core/v1/persistent_volume_claim.py
idem_k8s/exec/k8s/core/v1/service.py
idem_k8s/exec/k8s/rbac/v1/role_binding.py
idem_k8s/states/k8s/init.py
idem_k8s/states/k8s/apiregistration_k8s_io/v1/api_service.py
idem_k8s/states/k8s/apps/v1/daemon_set.py
idem_k8s/states/k8s/apps/v1/deployment.py
idem_k8s/states/k8s/core/v1/config_map.py
idem_k8s/states/k8s/core/v1/namespace.py
idem_k8s/states/k8s/core/v1/persistent_volume_claim.py
idem_k8s/states/k8s/core/v1/secret.py
idem_k8s/states/k8s/core/v1/service.py
idem_k8s/states/k8s/core/v1/service_account.py
idem_k8s/states/k8s/rbac/v1/cluster_role.py
idem_k8s/states/k8s/rbac/v1/cluster_role_binding.py
idem_k8s/states/k8s/rbac/v1/role_binding.py
idem_k8s/states/k8s/storage_k8s_io/v1/storage_class.py
idem_k8s/tool/k8s/client.py
idem_k8s/tool/k8s/comment_utils.py
idem_k8s/tool/k8s/custom_waiter.py
idem_k8s/tool/k8s/marshaller.py
idem_k8s/tool/k8s/resolve.py
idem_k8s/tool/k8s/state_utils.py
idem_k8s/tool/k8s/test_state_utils.py
idem_k8s/tool/k8s/waiter_utils.py
idem_k8s/tool/k8s/apiregistration_k8s_io/v1/api_service_utils.py
idem_k8s/tool/k8s/apps/v1/daemon_set_utils.py
idem_k8s/tool/k8s/apps/v1/deployment_utils.py
idem_k8s/tool/k8s/core/v1/config_map_utils.py
idem_k8s/tool/k8s/core/v1/namespace_utils.py
idem_k8s/tool/k8s/core/v1/persistent_volume_claim_utils.py
idem_k8s/tool/k8s/core/v1/secret_utils.py
idem_k8s/tool/k8s/core/v1/service_account_utils.py
idem_k8s/tool/k8s/core/v1/service_utils.py
idem_k8s/tool/k8s/rbac/v1/cluster_role_binding_utils.py
idem_k8s/tool/k8s/rbac/v1/cluster_role_utils.py
idem_k8s/tool/k8s/rbac/v1/role_binding_utils.py
idem_k8s/tool/k8s/storage_k8s_io/v1/storage_class_utils.py
idem_k8s-2.0.0.dist-info/LICENSE
idem_k8s-2.0.0.dist-info/METADATA
idem_k8s-2.0.0.dist-info/WHEEL
idem_k8s-2.0.0.dist-info/entry_points.txt
idem_k8s-2.0.0.dist-info/top_level.txt
idem_k8s-2.0.0.dist-info/RECORD
